README.md
setup.cfg
setup.py
align1d/__init__.py
align1d/align.py
align1d/setup.py
align1d.egg-info/PKG-INFO
align1d.egg-info/SOURCES.txt
align1d.egg-info/dependency_links.txt
align1d.egg-info/requires.txt
align1d.egg-info/top_level.txt