Metadata-Version: 2.1
Name: align1d
Version: 2.3.0
Summary: A small package for 1d aligment in cuda
Home-page: https://github.com/frostinassiky/gtad
Author: Frost Mengmeng Xu
Author-email: xu.frost@gmail.com
License: Apache License
Download-URL: https://github.com/frostinassiky/align1d/archive/2.3.0.tar.gz
Keywords: alignment,1d,temporal
Platform: UNKNOWN
Classifier: Development Status :: 3 - Alpha
Classifier: Intended Audience :: Developers
Classifier: Topic :: Software Development :: Build Tools
Classifier: License :: OSI Approved :: MIT License
Classifier: Programming Language :: Python :: 3.5
Classifier: Programming Language :: Python :: 3.6
Classifier: Programming Language :: Python :: 3.7
